ebs_init_mcp/__init__.py
ebs_init_mcp/aws_clients.py
ebs_init_mcp/estimation.py
ebs_init_mcp/initialization.py
ebs_init_mcp/server.py
ebs_init_mcp/server.py.backup
ebs_init_mcp/status.py
ebs_init_mcp/throughput.py
ebs_init_mcp/utils.py
ebs_initializer_mcp-0.7.13.dist-info/METADATA
ebs_initializer_mcp-0.7.13.dist-info/WHEEL
ebs_initializer_mcp-0.7.13.dist-info/entry_points.txt
ebs_initializer_mcp-0.7.13.dist-info/licenses/LICENSE
ebs_initializer_mcp-0.7.13.dist-info/RECORD
