Metadata-Version: 2.4
Name: ebs-initializer-mcp
Version: 0.7.13
Summary: MCP server for AWS EBS volume initialization
Project-URL: Repository, https://github.com/jsk6387/ebs_init_mcp
Project-URL: Bug Reports, https://github.com/jsk6387/ebs_init_mcp/issues
Author-email: sangkyuu <jsk6387@naver.com>
License: MIT
License-File: LICENSE
Keywords: aws,ebs,fastmcp,initialization,mcp,volume
Classifier: Development Status :: 4 - Beta
Classifier: Intended Audience :: System Administrators
Classifier: License :: OSI Approved :: MIT License
Classifier: Programming Language :: Python :: 3
Classifier: Programming Language :: Python :: 3.10
Classifier: Programming Language :: Python :: 3.11
Classifier: Programming Language :: Python :: 3.12
Classifier: Topic :: System :: Systems Administration
Classifier: Topic :: Utilities
Requires-Python: >=3.10
Requires-Dist: boto3>=1.4.0
Requires-Dist: mcp[cli]>=0.8.0
Provides-Extra: dev
Requires-Dist: black>=23.0.0; extra == 'dev'
Requires-Dist: pytest>=7.0.0; extra == 'dev'
Requires-Dist: ruff>=0.1.0; extra == 'dev'
